xserializer/__init__.py
xserializer/__version__.py
xserializer-0.0.1.dist-info/LICENSE
xserializer-0.0.1.dist-info/METADATA
xserializer-0.0.1.dist-info/WHEEL
xserializer-0.0.1.dist-info/top_level.txt
xserializer-0.0.1.dist-info/zip-safe
xserializer-0.0.1.dist-info/RECORD
